intros_MaxEnt-0.9.91.dist-info/METADATA
intros_MaxEnt-0.9.91.dist-info/RECORD
intros_MaxEnt-0.9.91.dist-info/WHEEL
intros_MaxEnt-0.9.91.dist-info/top_level.txt
introsmaxent/__init__.py
introsmaxent/background.py
introsmaxent/darwincore.py
introsmaxent/features.py
introsmaxent/geocode.py
introsmaxent/lineargrid.py
introsmaxent/location.py
introsmaxent/model.py
introsmaxent/observations.py
introsmaxent/podata.py
introsmaxent/solver.py
introsmaxent/test_geocode.py
introsmaxent/test_model.py
introsmaxent/test_solver.py
introsmaxent/utils.py
