Metadata-Version: 1.2
Name: intros-MaxEnt
Version: 0.9.91
Summary: A MaxEnt package with introspection for ecological niche modeling.
Home-page: https://wholetale.org
Author: Santiago Nunez-Corrales
Author-email: nunezco2@illinois.edu
License: LICENSE.txt
Platform: UNKNOWN
Requires-Python: >3.4
